CHANGELOG
LICENSE
MANIFEST.in
README.rst
requirements-performance.txt
requirements.txt
setup.py
dockerscan/__init__.py
dockerscan/__main__.py
dockerscan.egg-info/PKG-INFO
dockerscan.egg-info/SOURCES.txt
dockerscan.egg-info/dependency_links.txt
dockerscan.egg-info/entry_points.txt
dockerscan.egg-info/requires.txt
dockerscan.egg-info/top_level.txt
dockerscan/actions/__init__.py
dockerscan/actions/cli.py
dockerscan/actions/helpers.py
dockerscan/actions/image/__init__.py
dockerscan/actions/image/api.py
dockerscan/actions/image/cli.py
dockerscan/actions/image/console.py
dockerscan/actions/image/docker_api.py
dockerscan/actions/image/image_analyzer.py
dockerscan/actions/image/model.py
dockerscan/actions/image/modifiers/__init__.py
dockerscan/actions/image/modifiers/api.py
dockerscan/actions/image/modifiers/api_.py
dockerscan/actions/image/modifiers/cli.py
dockerscan/actions/image/modifiers/console.py
dockerscan/actions/image/modifiers/model.py
dockerscan/actions/image/modifiers/shells/reverse_shell.so
dockerscan/actions/registry/__init__.py
dockerscan/actions/registry/api.py
dockerscan/actions/registry/cli.py
dockerscan/actions/registry/console.py
dockerscan/actions/registry/model.py
dockerscan/actions/registry/libs/__init__.py
dockerscan/actions/registry/libs/helpers.py
dockerscan/actions/registry/libs/registry_v2.py
dockerscan/actions/scan/__init__.py
dockerscan/actions/scan/api.py
dockerscan/actions/scan/cli.py
dockerscan/actions/scan/console.py
dockerscan/actions/scan/model.py
dockerscan/core/__init__.py
dockerscan/core/exceptions.py
dockerscan/core/helpers.py
dockerscan/core/logger.py
dockerscan/core/model.py
dockerscan/core/shared_cmd_options.py
test/__init__.py
test/unittesting/__init__.py
test/unittesting/actions/__init__.py
test/unittesting/actions/default/__init__.py
test/unittesting/actions/default/api/__init__.py
test/unittesting/actions/default/api/test_run_dockerscan.py
test/unittesting/actions/default/cli/__init__.py
test/unittesting/actions/default/cli/test_cli.py
test/unittesting/actions/default/cli/test_cli_info.py
test/unittesting/core/__init__.py
test/unittesting/core/helpers/__init__.py
test/unittesting/core/helpers/test_dict_to_obj.py
