Metadata-Version: 1.1
Name: dockerscan
Version: 1.0.0a3
Summary: A Docker analysis tools
Home-page: https://github.com/cr0hn/dockerscan
Author: Daniel Garcia (cr0hn) / Roberto Munoz (robskye)
Author-email: cr0hn@cr0hn.com
License: BSD
Platform: UNKNOWN
Classifier: Environment :: Console
Classifier: Intended Audience :: System Administrators
Classifier: Intended Audience :: Other Audience
Classifier: License :: OSI Approved :: BSD License
Classifier: Operating System :: MacOS
Classifier: Operating System :: Microsoft :: Windows
Classifier: Operating System :: POSIX
Classifier: Programming Language :: Python :: 3.5
Classifier: Topic :: Security
